license
setup.py
obfupy/__init__.py
obfupy/document.py
obfupy/documentmanager.py
obfupy/util.py
obfupy.egg-info/PKG-INFO
obfupy.egg-info/SOURCES.txt
obfupy.egg-info/dependency_links.txt
obfupy.egg-info/top_level.txt
obfupy/transformers/__init__.py
obfupy/transformers/codec.py
obfupy/transformers/formatter.py
obfupy/transformers/replacer.py
obfupy/transformers/rewriter.py
obfupy/transformers/internal/__init__.py
obfupy/transformers/internal/astutil.py
obfupy/transformers/internal/builtinfunctions.py
obfupy/transformers/internal/byteencryptioncodec.py
obfupy/transformers/internal/callbackdata.py
obfupy/transformers/internal/iformatter.py
obfupy/transformers/internal/irewriter.py
obfupy/transformers/internal/optionsutil.py
obfupy/transformers/internal/reentryguard.py
obfupy/transformers/internal/util.py
obfupy/transformers/internal/rewriter/__init__.py
obfupy/transformers/internal/rewriter/codeblockmaker.py
obfupy/transformers/internal/rewriter/constantmanager.py
obfupy/transformers/internal/rewriter/context.py
obfupy/transformers/internal/rewriter/extranodemanager.py
obfupy/transformers/internal/rewriter/functionrewriter.py
obfupy/transformers/internal/rewriter/gotowithif.py
obfupy/transformers/internal/rewriter/ifrewriter.py
obfupy/transformers/internal/rewriter/negationmaker.py
obfupy/transformers/internal/rewriter/nopmaker.py
obfupy/transformers/internal/rewriter/rewriterutil.py
obfupy/transformers/internal/rewriter/truemaker.py
obfupy/transformers/utils/__init__.py
obfupy/transformers/utils/codecproviders.py
obfupy/transformers/utils/stringencoders.py