Metadata-Version: 2.1
Name: obfupy
Version: 0.1.1
Summary: obfupy is a Python 3 library that can obfuscate whole Python 3 projects, transform the source code to obfuscated and hard to understand code. obfupy aims to produce correct and functional code.
Home-page: https://github.com/wqking/obfupy
Author: wqking
Author-email: wqking@NOSPAMoutlook.com
License: UNKNOWN
Platform: any
Classifier: Programming Language :: Python :: 3
Classifier: License :: OSI Approved :: Apache Software License
Classifier: Operating System :: OS Independent
Requires-Python: >=3.9
License-File: license
